flowerpower_mqtt/__init__.py
flowerpower_mqtt/cli.py
flowerpower_mqtt/client.py
flowerpower_mqtt/config.py
flowerpower_mqtt/exceptions.py
flowerpower_mqtt/job_handler.py
flowerpower_mqtt/listener.py
flowerpower_mqtt/py.typed
flowerpower_mqtt-0.2.2.dist-info/WHEEL
flowerpower_mqtt-0.2.2.dist-info/entry_points.txt
flowerpower_mqtt-0.2.2.dist-info/METADATA
flowerpower_mqtt-0.2.2.dist-info/RECORD
