Metadata-Version: 2.3
Name: flowerpower-mqtt
Version: 0.2.2
Summary: MQTT plugin for FlowerPower - trigger pipeline execution on MQTT messages
Author: legout
Author-email: legout <ligno.blades@gmail.com>
Requires-Dist: flowerpower>=0.20.0
Requires-Dist: aiomqtt>=2.0.0
Requires-Dist: redis>=4.0.0
Requires-Dist: rq>=1.15.0
Requires-Dist: msgspec>=0.18.0
Requires-Dist: pyyaml>=6.0.0
Requires-Dist: msgpack>=1.0.0
Requires-Dist: protobuf>=4.0.0
Requires-Dist: pyarrow>=20.0.0
Requires-Dist: typer>=0.16.0
Requires-Dist: rich>=13.0.0
Requires-Dist: pytest>=7.0.0 ; extra == 'dev'
Requires-Dist: pytest-asyncio>=0.21.0 ; extra == 'dev'
Requires-Dist: black>=23.0.0 ; extra == 'dev'
Requires-Dist: ruff>=0.1.0 ; extra == 'dev'
Requires-Dist: mypy>=1.5.0 ; extra == 'dev'
Requires-Python: >=3.11
Project-URL: Documentation, https://legout.github.io/flowerpower-mqtt/
Project-URL: Homepage, https://github.com/legout/flowerpower-mqtt
Project-URL: Issues, https://github.com/legout/flowerpower-mqtt/issues
Provides-Extra: dev
